mainframe/__init__.py
mainframe/components/__init__.py
mainframe/components/core.py
mainframe/components/noise.py
mainframe/core.py
mainframe-0.0.8.dist-info/WHEEL
mainframe-0.0.8.dist-info/METADATA
mainframe-0.0.8.dist-info/RECORD
