Metadata-Version: 2.1
Name: mainframe
Version: 0.0.8
Summary: Central Repo for datasets
License: MIT
Author: chrisaddy
Author-email: chris.william.addy@gmail.com
Requires-Python: >=3.8,<3.10
Classifier: License :: OSI Approved :: MIT License
Classifier: Programming Language :: Python :: 3
Classifier: Programming Language :: Python :: 3.8
Classifier: Programming Language :: Python :: 3.9
Requires-Dist: pydantic (>=1.9.1,<2.0.0)
Requires-Dist: pyro-ppl (>=1.8.1,<2.0.0)
